spellbot/__init__.py
spellbot/_version.py
spellbot/cli.py
spellbot/client.py
spellbot/database.py
spellbot/enums.py
spellbot/environment.py
spellbot/errors.py
spellbot/logs.py
spellbot/metrics.py
spellbot/operations.py
spellbot/settings.py
spellbot/shard_status.py
spellbot/utils.py
spellbot/actions/__init__.py
spellbot/actions/admin_action.py
spellbot/actions/base_action.py
spellbot/actions/block_action.py
spellbot/actions/leave_action.py
spellbot/actions/lfg_action.py
spellbot/actions/score_action.py
spellbot/actions/tasks_action.py
spellbot/actions/verify_action.py
spellbot/actions/watch_action.py
spellbot/cogs/__init__.py
spellbot/cogs/about_cog.py
spellbot/cogs/admin_cog.py
spellbot/cogs/block_cog.py
spellbot/cogs/events_cog.py
spellbot/cogs/leave_cog.py
spellbot/cogs/lfg_cog.py
spellbot/cogs/owner_cog.py
spellbot/cogs/score_cog.py
spellbot/cogs/tasks_cog.py
spellbot/cogs/verify_cog.py
spellbot/cogs/watch_cog.py
spellbot/integrations/__init__.py
spellbot/integrations/convoke.py
spellbot/integrations/girudo.py
spellbot/integrations/spelltable.py
spellbot/integrations/tablestream.py
spellbot/migrations/alembic.ini
spellbot/migrations/env.py
spellbot/migrations/script.py.mako
spellbot/migrations/versions/01766a5fb976_support_multiple_queues.py
spellbot/migrations/versions/053fd7a31881_disable_require_confirmation.py
spellbot/migrations/versions/0a69d68c3feb_add_note_to_tokens_table.py
spellbot/migrations/versions/0a7382dbcae6_adds_game_password_support.py
spellbot/migrations/versions/1503d49ae8e1_adds_created_at_and_updated_at_to_more_.py
spellbot/migrations/versions/208851cc40e3_adds_banned_to_guild.py
spellbot/migrations/versions/2179aedacbff_rename_column_game_link.py
spellbot/migrations/versions/2bf551e10a79_adds_play_pins.py
spellbot/migrations/versions/385c969728ed_add_vc_suggestion_category_prefix.py
spellbot/migrations/versions/389819d6480d_adds_pin_verification.py
spellbot/migrations/versions/3a2194f29016_remove_suggest_voice_channel_column.py
spellbot-17.10.1.dist-info/METADATA
spellbot-17.10.1.dist-info/WHEEL
spellbot-17.10.1.dist-info/entry_points.txt
spellbot-17.10.1.dist-info/licenses/LICENSE.md
spellbot-17.10.1.dist-info/RECORD
