Metadata-Version: 2.4
Name: spellbot
Version: 17.10.1
Summary: The Discord bot for SpellTable
Project-URL: homepage, http://spellbot.io/
Project-URL: repository, https://github.com/lexicalunit/spellbot
Author-email: Amy Troschinetz <spellbot@lexicalunit.com>
License: MIT
License-File: LICENSE.md
Keywords: SpellTable,bot,discord,magic,mtg
Classifier: Development Status :: 4 - Beta
Classifier: Intended Audience :: End Users/Desktop
Classifier: License :: OSI Approved :: MIT License
Classifier: Programming Language :: Python :: 3.13
Classifier: Topic :: Communications :: Chat
Classifier: Topic :: Games/Entertainment :: Board Games
Requires-Python: <4,>=3.13
Requires-Dist: aiohttp-jinja2>=1.6
Requires-Dist: aiohttp>=3.9.4
Requires-Dist: alembic>=1.13.1
Requires-Dist: asgiref>=3.8.1
Requires-Dist: attrs>=23.2.0
Requires-Dist: babel>=2.14.0
Requires-Dist: cachetools>=5.5.0
Requires-Dist: certifi>=2024.2.2
Requires-Dist: click>=8.1.7
Requires-Dist: datadog>=0.49.1
Requires-Dist: ddtrace>=3.16.2
Requires-Dist: discord-py>=2.3.2
Requires-Dist: dunamai>=1.19.2
Requires-Dist: greenlet>=3.2.2
Requires-Dist: gunicorn>=21.2.0
Requires-Dist: httpx>=0.28.1
Requires-Dist: humanize>=4.9.0
Requires-Dist: hupper>=1.12.1
Requires-Dist: importlib-resources>=6.4.0
Requires-Dist: packaging>=24.0
Requires-Dist: psycopg[binary]>=3.2.9
Requires-Dist: python-dateutil>=2.8.2
Requires-Dist: python-dotenv>=1.0.1
Requires-Dist: python-json-logger>=3.3.0
Requires-Dist: pyyaml>=6.0.1
Requires-Dist: redis>=6.1.0
Requires-Dist: requests>=2.31.0
Requires-Dist: sqlalchemy-utils>=0.41.2
Requires-Dist: sqlalchemy>=2.0.41
Requires-Dist: supervisor>=4.2.5
Requires-Dist: tenacity>=9.0.0
Requires-Dist: toml>=0.10.2
Requires-Dist: uvloop>=0.19
Requires-Dist: wrapt<2,>=1
